pitopcli/__init__.py
pitopcli/__main__.py
pitopcli/battery.py
pitopcli/cli_base.py
pitopcli/deprecated_cli_runner.py
pitopcli/devices.py
pitopcli/display.py
pitopcli/formatter.py
pitopcli/imu.py
pitopcli/imu_calibration.py
pitopcli/oled.py
pitopcli/pitop.py
pitopcli/support.py
pitopcli/support_core/__init__.py
pitopcli/support_core/health_check.py
pitopcli/support_core/hub_communication.py
pitopcli/support_core/links.py
pitopcli/support_core/ptsoftware.py
pitopcli/support_core/systemd_service.py
pitopcli-0.34.3.post1.dist-info/METADATA
pitopcli-0.34.3.post1.dist-info/WHEEL
pitopcli-0.34.3.post1.dist-info/entry_points.txt
pitopcli-0.34.3.post1.dist-info/top_level.txt
pitopcli-0.34.3.post1.dist-info/RECORD
